<landuseAnalystScenario>
<model guid="413e50e4-ea3c-5966-9368-c5911690090c">\n  <name>Shuna · Chalcolithic · S17 · pop 100 · meat 20% · dairy 100% · feed</name>\n  <population>100</population>\n  <period>Chalcolithic</period>\n  <projection>32636</projection>\n  <easting>744800.0</easting>\n  <northing>3611100.0</northing>\n  <euclideanDistance>False</euclideanDistance>\n  <walkingTime>True</walkingTime>\n  <pathDistance>False</pathDistance>\n  <precision>5</precision>\n  <dietPercent>20</dietPercent>\n  <plantPercent>90</plantPercent>\n  <meatPercent>99</meatPercent>\n  <caloriesPerPersonDaily>2500</caloriesPerPersonDaily>\n  <baseOnPlants>False</baseOnPlants>\n  <includeDairy>True</includeDairy>\n  <limitDairy>False</limitDairy>\n  <limitDairyPercent>0</limitDairyPercent>\n  <dairyUtilisation>100</dairyUtilisation>\n  <commonLandValue>0.0</commonLandValue>\n  <commonLandAreaUnits>Hectare</commonLandAreaUnits>\n  <specificLandAreaUnits>Hectare</specificLandAreaUnits>\n  <specificLandEnergyType>KCalories</specificLandEnergyType>\n  <herdSize>0</herdSize>\n  <dairyUtilisation>100</dairyUtilisation>\n</model>\n  <selectedCrops>
    <selectedCrop cropGuid="a1b2c3d4-e5f6-7890-abcd-ef1234567890" parameterGuid="d9e8c7b6-a5f4-4e3d-b2c1-a0f9e8d7c6b5" />
    <selectedCrop cropGuid="b2c3d4e5-f6a7-8901-bcde-f23456789012" parameterGuid="e9f8d7c6-b5a4-4f3e-c2d1-b0a9f8e7d6c5" />
    <selectedCrop cropGuid="c3d4e5f6-a7b8-9012-cdef-34567890123a" parameterGuid="f8e7d6c5-a4b3-4e2d-c1b0-a9f8e7d6c5b4" />
    <selectedCrop cropGuid="d4e5f6a7-b8c9-0123-defg-4567890123bc" parameterGuid="a7f6e5d4-c3b2-4a1f-d0c9-b8a7f6e5d4c3" />
    <selectedCrop cropGuid="e5f6a7b8-c9d0-1234-efgh-567890123cde" parameterGuid="b6a5f4e3-d2c1-4b0a-e9d8-c7b6a5f4e3d2" />
    <selectedCrop cropGuid="f6a7b8c9-d0e1-2345-fghi-67890123def4" parameterGuid="c5b4a3f2-e1d0-4c9b-f8e7-d6c5b4a3f2e1" />
    <selectedCrop cropGuid="c9d0e1f2-a3b4-5678-ijkl-90123a789012" parameterGuid="d4c3b2a1-f0e9-4d8c-a7b6-e5d4c3b2a1f0" />
    <selectedCrop cropGuid="d0e1f2a3-b4c5-6789-jklm-0123b8901234" parameterGuid="e3d2c1b0-a9f8-4e7d-b6c5-a4f3e2d1c0b9" />
  </selectedCrops>
  <selectedAnimals>
    <selectedAnimal animalGuid="f1a2b3c4-d5e6-f7a8-b9c0-d1e2f3a4b5c6" parameterGuid="a1b2c3d4-e5f6-a7b8-c9d0-e1f2a3b4c5d6" />
    <selectedAnimal animalGuid="3b4c5d6e-7f8a-9b0c-1d2e-f3a4b5c6d7e8" parameterGuid="d1e2f3a4-b5c6-d7e8-f9a0-b1c2d3e4f5a6" />
    <selectedAnimal animalGuid="2a3b4c5d-6e7f-8a9b-0c1d-e2f3a4b5c6d7" parameterGuid="c1d2e3f4-a5b6-c7d8-e9f0-a1b2c3d4e5f6" />
    <selectedAnimal animalGuid="1f2a3b4c-5d6e-7f8a-9b0c-d1e2f3a4b5c6" parameterGuid="b1c2d3e4-f5a6-b7c8-d9e0-f1a2b3c4d5e6" />
  </selectedAnimals>
  <crops>
<crop guid="a1b2c3d4-e5f6-7890-abcd-ef1234567890">
  <name>Horse Bean</name>
  <description>Horse Bean crop</description>
  <cropYield>500</cropYield>
  <cropCalories>3000</cropCalories>
  <fodderProduction>300</fodderProduction>
  <fodderCalories>800</fodderCalories>
  <cropFodderEnergyType>KCalories</cropFodderEnergyType>
  <areaUnits>Hectare</areaUnits>
  <imageFile>/home/arkygeek/.landuseAnalyst/images/horsebean.png</imageFile>
</crop>
<cropParameter guid="d9e8c7b6-a5f4-4e3d-b2c1-a0f9e8d7c6b5">
  <name>Horse Bean · Chalcolithic params</name>
  <description>Horse Bean crop parameters</description>
  <crop>a1b2c3d4-e5f6-7890-abcd-ef1234567890</crop>
  <percentTameCrop>1.09</percentTameCrop>
  <spoilage>30</spoilage>
  <reseed>20</reseed>
  <cropRotation>1</cropRotation>
  <fallowRatio>1.0</fallowRatio>
  <fallowValue>500</fallowValue>
  <fallowEnergyType>KCalories</fallowEnergyType>
  <areaUnits>Hectare</areaUnits>
  <useCommonLand>1</useCommonLand>
  <useSpecificLand>0</useSpecificLand>
  <rasterName></rasterName>
  <preferredSlopeMin>0.0</preferredSlopeMin>
  <preferredSlopeMax>9.0</preferredSlopeMax>
</cropParameter>
<crop guid="b2c3d4e5-f6a7-8901-bcde-f23456789012">
  <name>Einkorn</name>
  <description>Einkorn wheat crop</description>
  <cropYield>500</cropYield>
  <cropCalories>3000</cropCalories>
  <fodderProduction>300</fodderProduction>
  <fodderCalories>800</fodderCalories>
  <cropFodderEnergyType>KCalories</cropFodderEnergyType>
  <areaUnits>Hectare</areaUnits>
  <imageFile>/home/arkygeek/.landuseAnalyst/images/einkorn.png</imageFile>
</crop>
<cropParameter guid="e9f8d7c6-b5a4-4f3e-c2d1-b0a9f8e7d6c5">
  <name>Einkorn · Chalcolithic params</name>
  <description>Einkorn crop parameters</description>
  <crop>b2c3d4e5-f6a7-8901-bcde-f23456789012</crop>
  <percentTameCrop>5.47</percentTameCrop>
  <spoilage>30</spoilage>
  <reseed>20</reseed>
  <cropRotation>1</cropRotation>
  <fallowRatio>1.0</fallowRatio>
  <fallowValue>500</fallowValue>
  <fallowEnergyType>KCalories</fallowEnergyType>
  <areaUnits>Hectare</areaUnits>
  <useCommonLand>1</useCommonLand>
  <useSpecificLand>0</useSpecificLand>
  <rasterName></rasterName>
  <preferredSlopeMin>0.0</preferredSlopeMin>
  <preferredSlopeMax>9.0</preferredSlopeMax>
</cropParameter>
<crop guid="c3d4e5f6-a7b8-9012-cdef-34567890123a">
  <name>Emmer</name>
  <description>Emmer wheat crop</description>
  <cropYield>500</cropYield>
  <cropCalories>3000</cropCalories>
  <fodderProduction>300</fodderProduction>
  <fodderCalories>800</fodderCalories>
  <cropFodderEnergyType>KCalories</cropFodderEnergyType>
  <areaUnits>Hectare</areaUnits>
  <imageFile>/home/arkygeek/.landuseAnalyst/images/emmer.png</imageFile>
</crop>
<cropParameter guid="f8e7d6c5-a4b3-4e2d-c1b0-a9f8e7d6c5b4">
  <name>Emmer · Chalcolithic params</name>
  <description>Emmer crop parameters</description>
  <crop>c3d4e5f6-a7b8-9012-cdef-34567890123a</crop>
  <percentTameCrop>52.52</percentTameCrop>
  <spoilage>30</spoilage>
  <reseed>20</reseed>
  <cropRotation>1</cropRotation>
  <fallowRatio>1.0</fallowRatio>
  <fallowValue>500</fallowValue>
  <fallowEnergyType>KCalories</fallowEnergyType>
  <areaUnits>Hectare</areaUnits>
  <useCommonLand>1</useCommonLand>
  <useSpecificLand>0</useSpecificLand>
  <rasterName></rasterName>
  <preferredSlopeMin>0.0</preferredSlopeMin>
  <preferredSlopeMax>9.0</preferredSlopeMax>
</cropParameter>
<crop guid="d4e5f6a7-b8c9-0123-defg-4567890123bc">
  <name>Lentils</name>
  <description>Lentils crop</description>
  <cropYield>300</cropYield>
  <cropCalories>3000</cropCalories>
  <fodderProduction>300</fodderProduction>
  <fodderCalories>800</fodderCalories>
  <cropFodderEnergyType>KCalories</cropFodderEnergyType>
  <areaUnits>Hectare</areaUnits>
  <imageFile>/home/arkygeek/.landuseAnalyst/images/lentils.png</imageFile>
</crop>
<cropParameter guid="a7f6e5d4-c3b2-4a1f-d0c9-b8a7f6e5d4c3">
  <name>Lentils · Chalcolithic params</name>
  <description>Lentils crop parameters</description>
  <crop>d4e5f6a7-b8c9-0123-defg-4567890123bc</crop>
  <percentTameCrop>1.09</percentTameCrop>
  <spoilage>30</spoilage>
  <reseed>20</reseed>
  <cropRotation>1</cropRotation>
  <fallowRatio>1.0</fallowRatio>
  <fallowValue>500</fallowValue>
  <fallowEnergyType>KCalories</fallowEnergyType>
  <areaUnits>Hectare</areaUnits>
  <useCommonLand>1</useCommonLand>
  <useSpecificLand>0</useSpecificLand>
  <rasterName></rasterName>
  <preferredSlopeMin>0.0</preferredSlopeMin>
  <preferredSlopeMax>9.0</preferredSlopeMax>
</cropParameter>
<crop guid="e5f6a7b8-c9d0-1234-efgh-567890123cde">
  <name>Peas</name>
  <description>Peas crop</description>
  <cropYield>150</cropYield>
  <cropCalories>3250</cropCalories>
  <fodderProduction>100</fodderProduction>
  <fodderCalories>800</fodderCalories>
  <cropFodderEnergyType>KCalories</cropFodderEnergyType>
  <areaUnits>Hectare</areaUnits>
  <imageFile>/home/arkygeek/.landuseAnalyst/images/peas.png</imageFile>
</crop>
<cropParameter guid="b6a5f4e3-d2c1-4b0a-e9d8-c7b6a5f4e3d2">
  <name>Peas · Chalcolithic params</name>
  <description>Peas crop parameters</description>
  <crop>e5f6a7b8-c9d0-1234-efgh-567890123cde</crop>
  <percentTameCrop>3.28</percentTameCrop>
  <spoilage>30</spoilage>
  <reseed>20</reseed>
  <cropRotation>1</cropRotation>
  <fallowRatio>1.0</fallowRatio>
  <fallowValue>500</fallowValue>
  <fallowEnergyType>KCalories</fallowEnergyType>
  <areaUnits>Hectare</areaUnits>
  <useCommonLand>1</useCommonLand>
  <useSpecificLand>0</useSpecificLand>
  <rasterName></rasterName>
  <preferredSlopeMin>0.0</preferredSlopeMin>
  <preferredSlopeMax>9.0</preferredSlopeMax>
</cropParameter>
<crop guid="f6a7b8c9-d0e1-2345-fghi-67890123def4">
  <name>Olives</name>
  <description>Olives crop</description>
  <cropYield>600</cropYield>
  <cropCalories>4000</cropCalories>
  <fodderProduction>0</fodderProduction>
  <fodderCalories>800</fodderCalories>
  <cropFodderEnergyType>KCalories</cropFodderEnergyType>
  <areaUnits>Hectare</areaUnits>
  <imageFile>/home/arkygeek/.landuseAnalyst/images/olives.png</imageFile>
</crop>
<cropParameter guid="c5b4a3f2-e1d0-4c9b-f8e7-d6c5b4a3f2e1">
  <name>Olives · Chalcolithic params</name>
  <description>Olives crop parameters</description>
  <crop>f6a7b8c9-d0e1-2345-fghi-67890123def4</crop>
  <percentTameCrop>1.53</percentTameCrop>
  <spoilage>30</spoilage>
  <reseed>0</reseed>
  <cropRotation>0</cropRotation>
  <fallowRatio>0.0</fallowRatio>
  <fallowValue>500</fallowValue>
  <fallowEnergyType>KCalories</fallowEnergyType>
  <areaUnits>Hectare</areaUnits>
  <useCommonLand>1</useCommonLand>
  <useSpecificLand>0</useSpecificLand>
  <rasterName></rasterName>
  <preferredSlopeMin>0.0</preferredSlopeMin>
  <preferredSlopeMax>9.0</preferredSlopeMax>
</cropParameter>
<crop guid="c9d0e1f2-a3b4-5678-ijkl-90123a789012">
  <name>Bitter Vetch</name>
  <description>Bitter Vetch crop</description>
  <cropYield>400</cropYield>
  <cropCalories>3000</cropCalories>
  <fodderProduction>300</fodderProduction>
  <fodderCalories>800</fodderCalories>
  <cropFodderEnergyType>KCalories</cropFodderEnergyType>
  <areaUnits>Hectare</areaUnits>
  <imageFile>/home/arkygeek/.landuseAnalyst/images/bittervetch.png</imageFile>
</crop>
<cropParameter guid="d4c3b2a1-f0e9-4d8c-a7b6-e5d4c3b2a1f0">
  <name>Bitter Vetch · Chalcolithic params</name>
  <description>Bitter Vetch crop parameters</description>
  <crop>c9d0e1f2-a3b4-5678-ijkl-90123a789012</crop>
  <percentTameCrop>2.19</percentTameCrop>
  <spoilage>30</spoilage>
  <reseed>20</reseed>
  <cropRotation>1</cropRotation>
  <fallowRatio>1.0</fallowRatio>
  <fallowValue>500</fallowValue>
  <fallowEnergyType>KCalories</fallowEnergyType>
  <areaUnits>Hectare</areaUnits>
  <useCommonLand>1</useCommonLand>
  <useSpecificLand>0</useSpecificLand>
  <rasterName></rasterName>
  <preferredSlopeMin>0.0</preferredSlopeMin>
  <preferredSlopeMax>9.0</preferredSlopeMax>
</cropParameter>
<crop guid="d0e1f2a3-b4c5-6789-jklm-0123b8901234">
  <name>Barley</name>
  <description>Barley crop</description>
  <cropYield>500</cropYield>
  <cropCalories>3000</cropCalories>
  <fodderProduction>300</fodderProduction>
  <fodderCalories>1420</fodderCalories>
  <cropFodderEnergyType>KCalories</cropFodderEnergyType>
  <areaUnits>Hectare</areaUnits>
  <imageFile>/home/arkygeek/.landuseAnalyst/images/barley.png</imageFile>
</crop>
<cropParameter guid="e3d2c1b0-a9f8-4e7d-b6c5-a4f3e2d1c0b9">
  <name>Barley · Chalcolithic params</name>
  <description>Barley crop parameters</description>
  <crop>d0e1f2a3-b4c5-6789-jklm-0123b8901234</crop>
  <percentTameCrop>32.83</percentTameCrop>
  <spoilage>30</spoilage>
  <reseed>20</reseed>
  <cropRotation>1</cropRotation>
  <fallowRatio>1.0</fallowRatio>
  <fallowValue>500</fallowValue>
  <fallowEnergyType>KCalories</fallowEnergyType>
  <areaUnits>Hectare</areaUnits>
  <useCommonLand>1</useCommonLand>
  <useSpecificLand>0</useSpecificLand>
  <rasterName></rasterName>
  <preferredSlopeMin>0.0</preferredSlopeMin>
  <preferredSlopeMax>9.0</preferredSlopeMax>
</cropParameter>
  </crops>
  <animals>
<animal guid="f1a2b3c4-d5e6-f7a8-b9c0-d1e2f3a4b5c6">
  <name>Sheep</name>
  <description>Sheep notes</description>
  <meatFoodValue>3200</meatFoodValue>
  <usableMeat>50</usableMeat>
  <killWeight>30</killWeight>
  <adultWeight>60</adultWeight>
  <conceptionEfficiency>80</conceptionEfficiency>
  <femalesToMales>20</femalesToMales>
  <growTime>40</growTime>
  <deathRate>30</deathRate>
  <feedEnergyType>KCalories</feedEnergyType>
  <gestating>3970</gestating>
  <lactating>5410</lactating>
  <maintenance>3200</maintenance>
  <juvenile>30</juvenile>
  <sexualMaturity>18</sexualMaturity>
  <breedingExpectancy>5</breedingExpectancy>
  <youngPerBirth>1</youngPerBirth>
  <weaningAge>60</weaningAge>
  <weaningWeight>8</weaningWeight>
  <gestationTime>150</gestationTime>
  <estrousCycle>21</estrousCycle>
  <lactationTime>210</lactationTime>
  <milk>False</milk>
  <milkGramsPerDay>940</milkGramsPerDay>
  <milkFoodValue>940</milkFoodValue>
  <fleece>False</fleece>
  <fleeceWeightKg>10.0</fleeceWeightKg>
  <imageFile>/home/arkygeek/.landuseAnalyst/images/sheep.png</imageFile>
</animal>
<animalParameter guid="a1b2c3d4-e5f6-a7b8-c9d0-e1f2a3b4c5d6">
  <name>Sheep · Chalcolithic · with feed</name>
  <description>test scenario 1</description>
  <animal>f1a2b3c4-d5e6-f7a8-b9c0-d1e2f3a4b5c6</animal>
  <percentTameMeat>3.59</percentTameMeat>
  <useCommonGrazingLand>0</useCommonGrazingLand>
  <useSpecificGrazingLand>1</useSpecificGrazingLand>
  <fodderUse>True</fodderUse>
  <fallowUsage>High</fallowUsage>
  <rasterName></rasterName>
  <areaUnits>Dunum</areaUnits>
  <energyType>KCalories</energyType>
  <specificLandEnergyType>KCalories</specificLandEnergyType>
  <valueCommonGrazingLand>1500</valueCommonGrazingLand>
  <valueSpecificGrazingLand>10</valueSpecificGrazingLand>
  <preferredSlopeMin>0.0</preferredSlopeMin>
  <preferredSlopeMax>15.0</preferredSlopeMax>
</animalParameter>
<animal guid="3b4c5d6e-7f8a-9b0c-1d2e-f3a4b5c6d7e8">
  <name>Goat</name>
  <description>Goat</description>
  <meatFoodValue>3200</meatFoodValue>
  <usableMeat>50</usableMeat>
  <killWeight>30</killWeight>
  <adultWeight>60</adultWeight>
  <conceptionEfficiency>80</conceptionEfficiency>
  <femalesToMales>20</femalesToMales>
  <growTime>40</growTime>
  <deathRate>30</deathRate>
  <feedEnergyType>KCalories</feedEnergyType>
  <gestating>3970</gestating>
  <lactating>5410</lactating>
  <maintenance>3200</maintenance>
  <juvenile>30</juvenile>
  <sexualMaturity>18</sexualMaturity>
  <breedingExpectancy>5</breedingExpectancy>
  <youngPerBirth>1</youngPerBirth>
  <weaningAge>60</weaningAge>
  <weaningWeight>8</weaningWeight>
  <gestationTime>150</gestationTime>
  <estrousCycle>21</estrousCycle>
  <lactationTime>210</lactationTime>
  <milk>False</milk>
  <milkGramsPerDay>900</milkGramsPerDay>
  <milkFoodValue>940</milkFoodValue>
  <fleece>False</fleece>
  <fleeceWeightKg>1.0</fleeceWeightKg>
  <imageFile>/home/arkygeek/.landuseAnalyst/images/goat_icon.png</imageFile>
</animal>
<animalParameter guid="d1e2f3a4-b5c6-d7e8-f9a0-b1c2d3e4f5a6">
  <name>Goat · Chalcolithic · with feed</name>
  <description>Parameters for Goat</description>
  <animal>3b4c5d6e-7f8a-9b0c-1d2e-f3a4b5c6d7e8</animal>
  <percentTameMeat>11.95</percentTameMeat>
  <useCommonGrazingLand>0</useCommonGrazingLand>
  <useSpecificGrazingLand>1</useSpecificGrazingLand>
  <fodderUse>True</fodderUse>
  <fallowUsage>High</fallowUsage>
  <rasterName></rasterName>
  <areaUnits>Dunum</areaUnits>
  <energyType>KCalories</energyType>
  <specificLandEnergyType>KCalories</specificLandEnergyType>
  <valueCommonGrazingLand>1500</valueCommonGrazingLand>
  <valueSpecificGrazingLand>10</valueSpecificGrazingLand>
  <preferredSlopeMin>0.0</preferredSlopeMin>
  <preferredSlopeMax>15.0</preferredSlopeMax>
</animalParameter>
<animal guid="2a3b4c5d-6e7f-8a9b-0c1d-e2f3a4b5c6d7">
  <name>Cow</name>
  <description>Cow</description>
  <meatFoodValue>3200</meatFoodValue>
  <usableMeat>50</usableMeat>
  <killWeight>400</killWeight>
  <adultWeight>625</adultWeight>
  <conceptionEfficiency>85</conceptionEfficiency>
  <femalesToMales>20</femalesToMales>
  <growTime>50</growTime>
  <deathRate>20</deathRate>
  <feedEnergyType>KCalories</feedEnergyType>
  <gestating>6000</gestating>
  <lactating>7500</lactating>
  <maintenance>5800</maintenance>
  <juvenile>30</juvenile>
  <sexualMaturity>18</sexualMaturity>
  <breedingExpectancy>8</breedingExpectancy>
  <youngPerBirth>1</youngPerBirth>
  <weaningAge>60</weaningAge>
  <weaningWeight>50</weaningWeight>
  <gestationTime>279</gestationTime>
  <estrousCycle>21</estrousCycle>
  <lactationTime>240</lactationTime>
  <milk>False</milk>
  <milkGramsPerDay>6000</milkGramsPerDay>
  <milkFoodValue>940</milkFoodValue>
  <fleece>False</fleece>
  <fleeceWeightKg>0.0</fleeceWeightKg>
  <imageFile>/home/arkygeek/.landuseAnalyst/images/cow.png</imageFile>
</animal>
<animalParameter guid="c1d2e3f4-a5b6-c7d8-e9f0-a1b2c3d4e5f6">
  <name>Cow · Chalcolithic · with feed</name>
  <description>Parameters for Cow</description>
  <animal>2a3b4c5d-6e7f-8a9b-0c1d-e2f3a4b5c6d7</animal>
  <percentTameMeat>47.81</percentTameMeat>
  <useCommonGrazingLand>0</useCommonGrazingLand>
  <useSpecificGrazingLand>1</useSpecificGrazingLand>
  <fodderUse>True</fodderUse>
  <fallowUsage>High</fallowUsage>
  <rasterName></rasterName>
  <areaUnits>Dunum</areaUnits>
  <energyType>KCalories</energyType>
  <specificLandEnergyType>KCalories</specificLandEnergyType>
  <valueCommonGrazingLand>1500</valueCommonGrazingLand>
  <valueSpecificGrazingLand>10</valueSpecificGrazingLand>
  <preferredSlopeMin>0.0</preferredSlopeMin>
  <preferredSlopeMax>15.0</preferredSlopeMax>
</animalParameter>
<animal guid="1f2a3b4c-5d6e-7f8a-9b0c-d1e2f3a4b5c6">
  <name>Pig</name>
  <description>Pig</description>
  <meatFoodValue>3200</meatFoodValue>
  <usableMeat>50</usableMeat>
  <killWeight>100</killWeight>
  <adultWeight>200</adultWeight>
  <conceptionEfficiency>70</conceptionEfficiency>
  <femalesToMales>20</femalesToMales>
  <growTime>40</growTime>
  <deathRate>30</deathRate>
  <feedEnergyType>KCalories</feedEnergyType>
  <gestating>3970</gestating>
  <lactating>5410</lactating>
  <maintenance>0</maintenance>
  <juvenile>30</juvenile>
  <sexualMaturity>18</sexualMaturity>
  <breedingExpectancy>5</breedingExpectancy>
  <youngPerBirth>6</youngPerBirth>
  <weaningAge>30</weaningAge>
  <weaningWeight>2</weaningWeight>
  <gestationTime>115</gestationTime>
  <estrousCycle>21</estrousCycle>
  <lactationTime>30</lactationTime>
  <milk>False</milk>
  <milkGramsPerDay>0</milkGramsPerDay>
  <milkFoodValue>0</milkFoodValue>
  <fleece>False</fleece>
  <fleeceWeightKg>0.0</fleeceWeightKg>
  <imageFile>/home/arkygeek/.landuseAnalyst/images/pig.png</imageFile>
</animal>
<animalParameter guid="b1c2d3e4-f5a6-b7c8-d9e0-f1a2b3c4d5e6">
  <name>Pig · Chalcolithic · with feed</name>
  <description>Parameters for Pig</description>
  <animal>1f2a3b4c-5d6e-7f8a-9b0c-d1e2f3a4b5c6</animal>
  <percentTameMeat>36.65</percentTameMeat>
  <useCommonGrazingLand>0</useCommonGrazingLand>
  <useSpecificGrazingLand>1</useSpecificGrazingLand>
  <fodderUse>True</fodderUse>
  <fallowUsage>High</fallowUsage>
  <rasterName></rasterName>
  <areaUnits>Dunum</areaUnits>
  <energyType>KCalories</energyType>
  <specificLandEnergyType>KCalories</specificLandEnergyType>
  <valueCommonGrazingLand>1500</valueCommonGrazingLand>
  <valueSpecificGrazingLand>10</valueSpecificGrazingLand>
  <preferredSlopeMin>0.0</preferredSlopeMin>
  <preferredSlopeMax>15.0</preferredSlopeMax>
</animalParameter>
  </animals>
</landuseAnalystScenario>
